TDAtaframe-0.3.2.dist-info/METADATA
TDAtaframe-0.3.2.dist-info/WHEEL
tdataframe.libs/libabsl_bad_optional_access-4af3b2cd.so.2407.0.0
tdataframe.libs/libabsl_bad_variant_access-1ced4b1e.so.2407.0.0
tdataframe.libs/libabsl_base-42c67d17.so.2407.0.0
tdataframe.libs/libabsl_city-4592e6fd.so.2407.0.0
tdataframe.libs/libabsl_civil_time-75fb1517.so.2407.0.0
tdataframe.libs/libabsl_cord-637812b6.so.2407.0.0
tdataframe.libs/libabsl_cord_internal-4a8a99c0.so.2407.0.0
tdataframe.libs/libabsl_cordz_functions-b163a44a.so.2407.0.0
tdataframe.libs/libabsl_cordz_handle-45bc937c.so.2407.0.0
tdataframe.libs/libabsl_cordz_info-2b12a473.so.2407.0.0
tdataframe.libs/libabsl_crc32c-5fb9943a.so.2407.0.0
tdataframe.libs/libabsl_crc_cord_state-9355929d.so.2407.0.0
tdataframe.libs/libabsl_crc_cpu_detect-44704496.so.2407.0.0
tdataframe.libs/libabsl_crc_internal-8a67d653.so.2407.0.0
tdataframe.libs/libabsl_debugging_internal-e6dac47d.so.2407.0.0
tdataframe.libs/libabsl_decode_rust_punycode-e7fa6952.so.2407.0.0
tdataframe.libs/libabsl_demangle_internal-3d92ce29.so.2407.0.0
tdataframe.libs/libabsl_demangle_rust-bf5d761f.so.2407.0.0
tdataframe.libs/libabsl_die_if_null-11740e1c.so.2407.0.0
tdataframe.libs/libabsl_examine_stack-349d062e.so.2407.0.0
tdataframe.libs/libabsl_exponential_biased-fa59bd27.so.2407.0.0
tdataframe.libs/libabsl_flags_commandlineflag-092abfa0.so.2407.0.0
tdataframe.libs/libabsl_flags_commandlineflag_internal-e7786d4d.so.2407.0.0
tdataframe.libs/libabsl_flags_config-88fb786b.so.2407.0.0
tdataframe.libs/libabsl_flags_internal-16877cf2.so.2407.0.0
tdataframe.libs/libabsl_flags_marshalling-e9920f8b.so.2407.0.0
tdataframe.libs/libabsl_flags_private_handle_accessor-94311995.so.2407.0.0
tdataframe.libs/libabsl_flags_program_name-9d5b39c0.so.2407.0.0
tdataframe.libs/libabsl_flags_reflection-c0c42035.so.2407.0.0
tdataframe.libs/libabsl_graphcycles_internal-d3c895a9.so.2407.0.0
tdataframe.libs/libabsl_hash-da39ffbf.so.2407.0.0
tdataframe.libs/libabsl_hashtablez_sampler-b2e77d79.so.2407.0.0
tdataframe.libs/libabsl_int128-c8aad110.so.2407.0.0
TDAtaframe-0.3.2.dist-info/RECORD
