Metadata-Version: 2.4
Name: TDAtaframe
Version: 0.3.2
Requires-Dist: polars >=1.14.0
Requires-Dist: pydantic >=2.8.0
Summary: A package to handle shape-matching for meshes
Author-email: Jack Ruder <jackruder@montana.edu>
Requires-Python: >=3.12
